enumap.py
enumap-1.5.0.dist-info/DESCRIPTION.rst
enumap-1.5.0.dist-info/METADATA
enumap-1.5.0.dist-info/RECORD
enumap-1.5.0.dist-info/WHEEL
enumap-1.5.0.dist-info/metadata.json
enumap-1.5.0.dist-info/top_level.txt
