Metadata-Version: 2.0
Name: enumap
Version: 1.5.0
Summary: Ordered collections inspired by Enum
Home-page: https://github.com/TadLeonard/enumap
Author: Tad Leonard
Author-email: tadfleonard@gmail.com
License: UNKNOWN
Download-URL: https://github.com/TadLeonard/enumap/archive/1.5.0.tar.gz
Platform: UNKNOWN
Classifier: Development Status :: 5 - Production/Stable
Classifier: Intended Audience :: Developers
Classifier: Operating System :: OS Independent
Classifier: Programming Language :: Python :: 3
Classifier: Programming Language :: Python :: 3 :: Only
